README.txt
setup.cfg
setup.py
docs/HISTORY.txt
raptus/__init__.py
raptus.headerfader.egg-info/PKG-INFO
raptus.headerfader.egg-info/SOURCES.txt
raptus.headerfader.egg-info/dependency_links.txt
raptus.headerfader.egg-info/entry_points.txt
raptus.headerfader.egg-info/namespace_packages.txt
raptus.headerfader.egg-info/not-zip-safe
raptus.headerfader.egg-info/requires.txt
raptus.headerfader.egg-info/top_level.txt
raptus/headerfader/__init__.py
raptus/headerfader/configure.zcml
raptus/headerfader/browser/__init__.py
raptus/headerfader/browser/configure.zcml
raptus/headerfader/browser/headerfader.init.js
raptus/headerfader/browser/headerfader.pt
raptus/headerfader/browser/headerfader.py
raptus/headerfader/profiles/default/cssregistry.xml
raptus/headerfader/profiles/default/jsregistry.xml
raptus/headerfader/profiles/default/metadata.xml
raptus/headerfader/profiles/default/propertiestool.xml
raptus/headerfader/profiles/default/skins.xml
raptus/headerfader/profiles/default/viewlets.xml
raptus/headerfader/skins/raptus_headerfader/raptus.headerfader.css.dtml