Metadata-Version: 1.0
Name: raptus.headerfader
Version: 1.0b4
Summary: Provides a header viewlet based on raptus.header which fades between the available images
Home-page: http://raptus.com
Author: Raptus AG
Author-email: dev@raptus.com
License: GPL
Platform: UNKNOWN
Classifier: Programming Language :: Python
Classifier: Topic :: Software Development :: Libraries :: Python Modules
